eotds_cli/__init__.py
eotds_cli/main.py
eotds_cli-0.1.0.dist-info/entry_points.txt
eotds_cli-0.1.0.dist-info/WHEEL
eotds_cli-0.1.0.dist-info/METADATA
eotds_cli-0.1.0.dist-info/RECORD
