Metadata-Version: 2.1
Name: eotds-cli
Version: 0.1.0
Summary: 
Author: Juan Sensio
Author-email: it@earthpulse.es
Requires-Python: >=3.8,<4.0
Classifier: Programming Language :: Python :: 3
Classifier: Programming Language :: Python :: 3.8
Classifier: Programming Language :: Python :: 3.9
Classifier: Programming Language :: Python :: 3.10
Requires-Dist: typer[all] (>=0.1.0,<0.2.0)
